redpandas/__init__.py
redpandas/redpd_build_station.py
redpandas/redpd_cohere.py
redpandas/redpd_config.py
redpandas/redpd_datawin.py
redpandas/redpd_df.py
redpandas/redpd_dq.py
redpandas/redpd_ensonify.py
redpandas/redpd_errors.py
redpandas/redpd_filter.py
redpandas/redpd_geospatial.py
redpandas/redpd_gravity.py
redpandas/redpd_iterator.py
redpandas/redpd_orientation.py
redpandas/redpd_preprocess.py
redpandas/redpd_report.py
redpandas/redpd_scales.py
redpandas/redpd_tfr.py
redpandas/redpd_xcorr.py
redpandas/redpd_plot/__init__.py
redpandas/redpd_plot/coherence.py
redpandas/redpd_plot/mesh.py
redpandas/redpd_plot/parameters.py
redpandas/redpd_plot/wiggles.py
redvox_pandas-1.5.1.dist-info/licenses/LICENSE
redvox_pandas-1.5.1.dist-info/METADATA
redvox_pandas-1.5.1.dist-info/WHEEL
redvox_pandas-1.5.1.dist-info/top_level.txt
redvox_pandas-1.5.1.dist-info/RECORD
