Metadata-Version: 2.4
Name: redvox-pandas
Version: 1.5.1
Summary: Library to streamline preprocessing of RedVox API 900 and API 1000 data
Author-email: "Infrasound Laboratory, University of Hawaii" <tyler@isla.hawaii.edu>
License: 
Project-URL: homepage, https://github.com/ISLA-UH/redpandas
Project-URL: PyPI, https://pypi.org/project/redpandas/
Requires-Python: >=3.8
License-File: LICENSE
Requires-Dist: matplotlib>=3.10.0
Requires-Dist: numpy>=2.2.1
Requires-Dist: obspy>=1.4.1
Requires-Dist: pandas>=2.2.2
Requires-Dist: pymap3d>=3.1.0
Requires-Dist: quantum-inferno>=1.1.3
Requires-Dist: redvox>=3.8.6
Requires-Dist: scipy>=1.15.0
Dynamic: license-file
